synthorus/__init__.py
synthorus/error.py
synthorus/dataset/__init__.py
synthorus/dataset/_dataset.py
synthorus/dataset/_dataset_impl/__init__.py
synthorus/dataset/_dataset_impl/_connection_params.py
synthorus/dataset/_dataset_impl/_query.py
synthorus/dataset/_dataset_impl/math_dataset.py
synthorus/dataset/_dataset_impl/odbc_dataset.py
synthorus/dataset/_dataset_impl/pandas_dataset.py
synthorus/dataset/_dataset_impl/postgres_dataset.py
synthorus/dataset/_dataset_impl/table_builder.py
synthorus/model/__init__.py
synthorus/model/dataset_cache.py
synthorus/model/dataset_spec.py
synthorus/model/dataset_spec_impl.py
synthorus/model/datasource_spec.py
synthorus/model/defaults.py
synthorus/model/make_model_index.py
synthorus/model/model_index.py
synthorus/model/model_spec.py
synthorus/noise/__init__.py
synthorus/noise/noiser.py
synthorus/noise/row_sampler.py
synthorus/noise/safe_random.py
synthorus/simulator/__init__.py
synthorus/simulator/condition_spec.py
synthorus/simulator/make_simulator_from_simulator_spec.py
synthorus/simulator/make_simulator_spec_from_model_spec.py
synthorus/simulator/no_sim_sampler.py
synthorus/simulator/pgm_sim_sampler.py
synthorus/simulator/sim_condition.py
synthorus/simulator/sim_entity.py
synthorus/simulator/sim_field.py
synthorus/simulator/sim_field_updaters.py
synthorus/simulator/sim_record.py
synthorus/simulator/sim_recorder.py
synthorus/simulator/simulator.py
synthorus/simulator/simulator_spec.py
synthorus/spec_file/__init__.py
synthorus/spec_file/find_datasource.py
synthorus/spec_file/interpret_spec_file.py
synthorus/spec_file/keys.py
synthorus/spec_file/spec_dict.py
synthorus/utils/__init__.py
synthorus/utils/clean_num.py
synthorus/utils/clean_state.py
synthorus/utils/config_help.py
synthorus/utils/const.py
synthorus/utils/data_catcher.py
synthorus/utils/dataframe_extras.py
synthorus/utils/dict_extras.py
synthorus/utils/math_extras.py
synthorus/utils/multiprocessing_extras.py
synthorus/utils/parse_formula.py
synthorus-0.0.0a13.dist-info/licenses/LICENSE.txt
synthorus-0.0.0a13.dist-info/METADATA
synthorus-0.0.0a13.dist-info/WHEEL
synthorus-0.0.0a13.dist-info/top_level.txt
synthorus-0.0.0a13.dist-info/RECORD
