Metadata-Version: 2.4
Name: synthorus
Version: 0.0.0a13
Summary: A Python package for synthetic data generation.
Author-email: Barry Drake <barry@synthorus.org>
License-Expression: MIT
Project-URL: Homepage, https://github.com/ropeless/synthorus
Project-URL: Issues, https://github.com/ropeless/synthorus/issues
Classifier: Programming Language :: Python :: 3
Classifier: Operating System :: OS Independent
Requires-Python: >=3.12
License-File: LICENSE.txt
Requires-Dist: compiled-knowledge
Requires-Dist: pandas
Requires-Dist: pyarrow
Requires-Dist: pyodbc
Requires-Dist: psycopg
Requires-Dist: psycopg-binary
Requires-Dist: xlsxwriter
Requires-Dist: pydantic
Dynamic: license-file
